{
    "items": [
        {
            "Video_kind": "youtube#video",
            "Video_ID": "YuuZLRAZkqQ",
            "Video_Title": "\ud83d\ude31\ud83d\udca5 Best Trick To Make Cropped Jacket From Puffer Jacket With A Belt #shorts",
            "Video_Timestamp": "2022-11-03T17:23:02Z",
            "Video_View_Count": 30462056,
            "Video_Likes": 534305
        },
        {
            "Video_kind": "youtube#video",
            "Video_ID": "IVmwRBJ_mr8",
            "Video_Title": "Folding hacks for T-shirts,hoodie,down jacket/organizing skills tips for clothes wardrobe/tiktok",
            "Video_Timestamp": "2022-12-12T11:03:20Z",
            "Video_View_Count": 2421080,
            "Video_Likes": 103754
        },
        {
            "Video_kind": "youtube#video",
            "Video_ID": "3UyGSGu9j1w",
            "Video_Title": "Top 5 Winter Jackets",
            "Video_Timestamp": "2022-12-28T16:39:26Z",
            "Video_View_Count": 1659571,
            "Video_Likes": 90547
        },
        {
            "Video_kind": "youtube#video",
            "Video_ID": "-Ogv5_xT6S4",
            "Video_Title": "The ONE Big Mistake That's Making You Colder",
            "Video_Timestamp": "2022-12-14T19:00:00Z",
            "Video_View_Count": 5229450,
            "Video_Likes": 89002
        },
        {
            "Video_kind": "youtube#video",
            "Video_ID": "FRR5gROjuok",
            "Video_Title": "The TRUTH About UNIQLO",
            "Video_Timestamp": "2022-09-14T15:00:08Z",
            "Video_View_Count": 1173248,
            "Video_Likes": 23678
        },
        {
            "Video_kind": "youtube#video",
            "Video_ID": "q2wvinLPcPY",
            "Video_Title": "3 Coats EVERY GUY Needs to Own #Shorts",
            "Video_Timestamp": "2022-12-15T15:30:09Z",
            "Video_View_Count": 314653,
            "Video_Likes": 17496
        },
        {
            "Video_kind": "youtube#video",
            "Video_ID": "KiE-vxKF_EQ",
            "Video_Title": "DOS & DON\u2019TS OF PUFFER COATS",
            "Video_Timestamp": "2022-02-15T16:02:41Z",
            "Video_View_Count": 538479,
            "Video_Likes": 16362
        },
        {
            "Video_kind": "youtube#video",
            "Video_ID": "hFIjS7CA5zs",
            "Video_Title": "$12 Hack Beats Expensive Down Jacket",
            "Video_Timestamp": "2022-02-23T19:00:13Z",
            "Video_View_Count": 910817,
            "Video_Likes": 16137
        },
        {
            "Video_kind": "youtube#video",
            "Video_ID": "MOJ1P1GDFkY",
            "Video_Title": "How To Style A Puffer Jacket! #fashion",
            "Video_Timestamp": "2022-11-26T16:23:39Z",
            "Video_View_Count": 353822,
            "Video_Likes": 12701
        },
        {
            "Video_kind": "youtube#video",
            "Video_ID": "L8MSoZ7yqiU",
            "Video_Title": "Uniqlo U Spring Summer 2022 Haul",
            "Video_Timestamp": "2022-03-05T18:06:47Z",
            "Video_View_Count": 400739,
            "Video_Likes": 12497
        },
        {
            "Video_kind": "youtube#video",
            "Video_ID": "2-L9smbdzp0",
            "Video_Title": "MF's wearing arc'teryx be like #shorts",
            "Video_Timestamp": "2022-07-31T18:57:51Z",
            "Video_View_Count": 447322,
            "Video_Likes": 11798
        },
        {
            "Video_kind": "youtube#video",
            "Video_ID": "wOx0FhZJXmY",
            "Video_Title": "\u3010\u30a2\u30d1\u30ec\u30eb\u793e\u9577\u304c\u6559\u3048\u308b\u3011\u30e2\u30c6\u308b\u30c0\u30a6\u30f3\u30b3\u30fc\u30c7\u306e\u30dd\u30a4\u30f3\u30c87\u9078\uff01\u30b3\u30ec\u306f\u7d76\u5bfe\u62bc\u3055\u3048\u3066\uff01",
            "Video_Timestamp": "2022-11-22T11:00:40Z",
            "Video_View_Count": 299740,
            "Video_Likes": 7268
        },
        {
            "Video_kind": "youtube#video",
            "Video_ID": "IiUgzAOiS80",
            "Video_Title": "2023\u2019s most OUTSTANDING puffy jackets",
            "Video_Timestamp": "2022-11-03T18:05:08Z",
            "Video_View_Count": 443878,
            "Video_Likes": 6031
        },
        {
            "Video_kind": "youtube#video",
            "Video_ID": "cNwjj56vOXk",
            "Video_Title": "BEST WINTER COATS for the COLDEST winter \u2744\ufe0f Reviewing Canada Goose, Northface and more!!",
            "Video_Timestamp": "2022-12-03T17:00:30Z",
            "Video_View_Count": 355919,
            "Video_Likes": 5586
        },
        {
            "Video_kind": "youtube#video",
            "Video_ID": "4AUhOMvJPxk",
            "Video_Title": "How to wash a down jacket!",
            "Video_Timestamp": "2022-08-06T06:23:48Z",
            "Video_View_Count": 239604,
            "Video_Likes": 5207
        },
        {
            "Video_kind": "youtube#video",
            "Video_ID": "YKL6D2ERJzQ",
            "Video_Title": "ARE YOU READY FOR WINTER? | MEN'S ESSENTIALS",
            "Video_Timestamp": "2022-12-18T12:00:14Z",
            "Video_View_Count": 112167,
            "Video_Likes": 4350
        },
        {
            "Video_kind": "youtube#video",
            "Video_ID": "u2jyDef9zN8",
            "Video_Title": "Why our new Jet-Black Puffer Jackets are \u00a3175?!",
            "Video_Timestamp": "2022-10-28T19:01:29Z",
            "Video_View_Count": 139565,
            "Video_Likes": 3320
        },
        {
            "Video_kind": "youtube#video",
            "Video_ID": "DJvSE0Lh0bA",
            "Video_Title": "This is what SHOPPING in Japan is like! Mega Uniqlo & Don Quijote Tokyo",
            "Video_Timestamp": "2022-11-05T09:40:18Z",
            "Video_View_Count": 217936,
            "Video_Likes": 2112
        },
        {
            "Video_kind": "youtube#video",
            "Video_ID": "iEHuBtqS_HE",
            "Video_Title": "Zara vs H&M vs Uniqlo I Which brand is better? I #zara I #H&M I #uniqlo",
            "Video_Timestamp": "2022-12-14T13:00:09Z",
            "Video_View_Count": 65347,
            "Video_Likes": 1989
        },
        {
            "Video_kind": "youtube#video",
            "Video_ID": "2HqkodISFnM",
            "Video_Title": "UNIQLO U FALL/WINTER TRY-ON HAUL & SHOPPING VLOG | Affordable Modest Outfits",
            "Video_Timestamp": "2022-10-08T14:00:02Z",
            "Video_View_Count": 134965,
            "Video_Likes": 1906
        },
        {
            "Video_kind": "youtube#video",
            "Video_ID": "udhjwHtEZcw",
            "Video_Title": "\u3010\u30e6\u30cb\u30af\u30edNG\u30a2\u30a6\u30bf\u30fc\u3011\u670d\u306e\u30d7\u30ed\u304c\u5fb9\u5e95\u89e3\u8aac\uff01\uff01\u30b3\u30ec\u306b\u306f\u6c17\u3092\u3064\u3051\u3066\uff01",
            "Video_Timestamp": "2022-12-26T10:30:19Z",
            "Video_View_Count": 255516,
            "Video_Likes": 1893
        },
        {
            "Video_kind": "youtube#video",
            "Video_ID": "nPg-IGLwh5s",
            "Video_Title": "PETITE Fall & Winter Outerwear Collection! Best Petite Clothing!",
            "Video_Timestamp": "2022-11-09T12:00:37Z",
            "Video_View_Count": 85154,
            "Video_Likes": 1304
        },
        {
            "Video_kind": "youtube#video",
            "Video_ID": "cWZ1Jcrmt9c",
            "Video_Title": "UNIQLO | How to wash your Ultra Light Down Jacket",
            "Video_Timestamp": "2022-02-01T14:19:16Z",
            "Video_View_Count": 174225,
            "Video_Likes": 1254
        },
        {
            "Video_kind": "youtube#video",
            "Video_ID": "O8WaFj8txuY",
            "Video_Title": "Trying on the viral Uniqlo trousers!",
            "Video_Timestamp": "2022-10-11T01:13:45Z",
            "Video_View_Count": 97667,
            "Video_Likes": 1245
        },
        {
            "Video_kind": "youtube#video",
            "Video_ID": "A_UU8uBUbfs",
            "Video_Title": "UNIQLO U FALL/WINTER TRY-ON HAUL & 10 OUTFIT IDEAS, Part 2 | Affordable Modest Outfits",
            "Video_Timestamp": "2022-10-25T17:58:41Z",
            "Video_View_Count": 46952,
            "Video_Likes": 1194
        },
        {
            "Video_kind": "youtube#video",
            "Video_ID": "iDdSw0KvFPg",
            "Video_Title": "\u9aa8\u30b9\u30c8\u304c\u8cb7\u3046\u3079\u304dUNIQLO\u7740\u75e9\u305b\u30c0\u30a6\u30f3\ud83c\udf84 #\u9aa8\u683c\u30b9\u30c8\u30ec\u30fc\u30c8 #\u30e6\u30cb\u30af\u30ed\u8cfc\u5165\u54c1 #\u9aa8\u683c\u8a3a\u65ad #\u30e6\u30cb\u30af\u30ed\u30b3\u30fc\u30c7",
            "Video_Timestamp": "2022-12-12T00:11:35Z",
            "Video_View_Count": 150345,
            "Video_Likes": 1190
        },
        {
            "Video_kind": "youtube#video",
            "Video_ID": "IPjCZmKz92k",
            "Video_Title": "Aritzia Super Puff vs. The North Face 1996 Puffer #shorts #winterjackets",
            "Video_Timestamp": "2022-12-25T20:50:48Z",
            "Video_View_Count": 53847,
            "Video_Likes": 1178
        },
        {
            "Video_kind": "youtube#video",
            "Video_ID": "w4r6qp3dOvk",
            "Video_Title": "UNIQLO WINTER 2022/2023 FAVORITES | Outfit Ideas For Freezing Winter Days | How to Stay Warm & Chic",
            "Video_Timestamp": "2022-12-23T22:58:33Z",
            "Video_View_Count": 31042,
            "Video_Likes": 1136
        },
        {
            "Video_kind": "youtube#video",
            "Video_ID": "s2MilOf2JFM",
            "Video_Title": "HOW TO WASH A DOWN JACKET the RIGHT WAY // 5 Simple Steps",
            "Video_Timestamp": "2022-12-09T19:00:30Z",
            "Video_View_Count": 88585,
            "Video_Likes": 1009
        },
        {
            "Video_kind": "youtube#video",
            "Video_ID": "otB5W40rbwE",
            "Video_Title": "5 Winter Jackets You Need In Your Wardrobe 2022",
            "Video_Timestamp": "2022-01-06T20:45:47Z",
            "Video_View_Count": 44236,
            "Video_Likes": 983
        },
        {
            "Video_kind": "youtube#video",
            "Video_ID": "CQ9YkpBQN9c",
            "Video_Title": "\u3010UNIQLO\u3011\u51ac\u306b\u5927\u6d3b\u8e8d\u306e\u30e6\u30cb\u30af\u30ed\u306e\u30c0\u30a6\u30f3\u3092\u4e00\u6319\u3054\u7d39\u4ecb\u3010\u30b3\u30b9\u30d1\u25ce\u3011",
            "Video_Timestamp": "2022-11-25T12:00:06Z",
            "Video_View_Count": 174323,
            "Video_Likes": 934
        },
        {
            "Video_kind": "youtube#video",
            "Video_ID": "VW94UkoVdJ8",
            "Video_Title": "Must Have Coats & Jackets for Fall/Winter 2022",
            "Video_Timestamp": "2022-10-16T17:00:16Z",
            "Video_View_Count": 63771,
            "Video_Likes": 926
        },
        {
            "Video_kind": "youtube#video",
            "Video_ID": "xBD0Mq6jlb4",
            "Video_Title": "ZARA. UNIQLO. COS &OTHER STORIES. \u0412\u0415\u0420\u0425\u041d\u042f\u042f \u041e\u0414\u0415\u0416\u0414\u0410. \u0428\u041e\u041f\u0418\u041d\u0413 \u0412\u041b\u041e\u0413\ud83c\udf42",
            "Video_Timestamp": "2022-09-22T15:00:39Z",
            "Video_View_Count": 23022,
            "Video_Likes": 868
        },
        {
            "Video_kind": "youtube#video",
            "Video_ID": "x0Y-BoQdxWc",
            "Video_Title": "WINTERJACKE? Die perfekten VIER (99\u20ac - 249\u20ac) - Nachhaltig, Billig, Zeitlos und Modisch!",
            "Video_Timestamp": "2022-11-27T09:48:01Z",
            "Video_View_Count": 13440,
            "Video_Likes": 811
        },
        {
            "Video_kind": "youtube#video",
            "Video_ID": "-maLksmEU0w",
            "Video_Title": "BEST Puffer Jackets Under \u00a3300 | HUGE Men's Puffer Jacket Haul (North Face, Napapijri, ARNE & More)",
            "Video_Timestamp": "2022-11-10T18:00:00Z",
            "Video_View_Count": 68829,
            "Video_Likes": 781
        },
        {
            "Video_kind": "youtube#video",
            "Video_ID": "QLYRKqGPRIw",
            "Video_Title": "Reviewing Uniqlo's Winter Clothes #shorts #fashion #shorts30",
            "Video_Timestamp": "2022-10-19T20:13:51Z",
            "Video_View_Count": 47923,
            "Video_Likes": 683
        },
        {
            "Video_kind": "youtube#video",
            "Video_ID": "wpCT-ZqzsNk",
            "Video_Title": "How to wash a down jacket (Stains/Re-puffing)",
            "Video_Timestamp": "2022-11-12T20:30:05Z",
            "Video_View_Count": 89111,
            "Video_Likes": 667
        },
        {
            "Video_kind": "youtube#video",
            "Video_ID": "UupP4lyi0ko",
            "Video_Title": "\u3010UNIQLO\u30fbGU\u30fbH\uff06M\u3011\u30d7\u30c1\u30d7\u30e9\u30fb\u30d5\u30a1\u30b9\u30c8\u30d5\u30a1\u30c3\u30b7\u30e7\u30f3\u3060\u3051\u3067\u51ac\u30b3\u30fc\u30c7\u30a3\u30cd\u30fc\u30c8\u3057\u3066\u307f\u305f\u3010\u30b3\u30b9\u30d1\u304c\u3059\u3054\u3044\u3011",
            "Video_Timestamp": "2022-12-05T12:00:23Z",
            "Video_View_Count": 80327,
            "Video_Likes": 574
        },
        {
            "Video_kind": "youtube#video",
            "Video_ID": "vSg4AdxJfiQ",
            "Video_Title": "\u3010\u7dcf\u984d150\u4e07\u3011\u6301\u3063\u3066\u308b\u30c0\u30a6\u30f3\u30b8\u30e3\u30b1\u30c3\u30c8\u5168\u3066\u7d39\u4ecb\u3057\u3066\u307f\u305f\uff01\u30ab\u30c3\u30b3\u826f\u3059\u304e\u308b\uff01\u5f8c\u7de8\uff01\u30ce\u30fc\u30b9\u30d5\u30a7\u30a4\u30b9\u3001\u30c0\u30a4\u30ef\u3001\u30e6\u30cb\u30af\u30ed\u3001\u30a2\u30fc\u30af\u30c6\u30ea\u30af\u30b9...etc",
            "Video_Timestamp": "2022-12-11T11:40:30Z",
            "Video_View_Count": 89946,
            "Video_Likes": 515
        },
        {
            "Video_kind": "youtube#video",
            "Video_ID": "yRCU8Zm125w",
            "Video_Title": "The Best Way To Fix Ripped Down Jacket | NO VISIBLE STITCHING/PATCH",
            "Video_Timestamp": "2022-05-06T13:19:17Z",
            "Video_View_Count": 115150,
            "Video_Likes": 382
        },
        {
            "Video_kind": "youtube#video",
            "Video_ID": "kzMBmizWmU0",
            "Video_Title": "UNIQLO FW 22 | die BESTEN PIECES | Knit, Rollkragen, Puffer Jacket | mubiix",
            "Video_Timestamp": "2022-10-25T16:00:29Z",
            "Video_View_Count": 7907,
            "Video_Likes": 377
        },
        {
            "Video_kind": "youtube#video",
            "Video_ID": "JgtSnKvuQus",
            "Video_Title": "DECATHLON FORCLAZ MT100 - A Decathlon Down Puffer Jacket Review!",
            "Video_Timestamp": "2022-03-01T16:42:41Z",
            "Video_View_Count": 33545,
            "Video_Likes": 352
        },
        {
            "Video_kind": "youtube#video",
            "Video_ID": "UC0HsBD-fV8",
            "Video_Title": "\uaca8\uc6b8\uc5d0 \uaf2d \uc785\uc5b4\ubd10\uc57c \ud560 \uc720\ub2c8\ud074\ub85c \ud328\ub529 2\uc885",
            "Video_Timestamp": "2022-11-12T11:15:21Z",
            "Video_View_Count": 39393,
            "Video_Likes": 281
        },
        {
            "Video_kind": "youtube#video",
            "Video_ID": "A6rzoNZxvlw",
            "Video_Title": "UNIQLO Ultra Light Jacket + Pants REVIEW | Uniqlo Suits | WORTH IT??",
            "Video_Timestamp": "2022-02-25T06:00:03Z",
            "Video_View_Count": 23981,
            "Video_Likes": 221
        },
        {
            "Video_kind": "youtube#video",
            "Video_ID": "0gOoEf284EY",
            "Video_Title": "UNIQLO\u306e\u30c0\u30a6\u30f3\u304c\u904e\u53bb\uff11\u3059\u304e\u3066\u2026#\u30e6\u30cb\u30af\u30ed#\u30a2\u30e9\u30d5\u30a9\u30fc#\u30a2\u30e9\u30b5\u30fc",
            "Video_Timestamp": "2022-11-22T11:00:00Z",
            "Video_View_Count": 36994,
            "Video_Likes": 193
        },
        {
            "Video_kind": "youtube#video",
            "Video_ID": "RylpMrRfz_c",
            "Video_Title": "the perfect black puffer jacket #shorts",
            "Video_Timestamp": "2022-10-12T16:42:30Z",
            "Video_View_Count": 14710,
            "Video_Likes": 193
        },
        {
            "Video_kind": "youtube#video",
            "Video_ID": "rfNCnhBRCHM",
            "Video_Title": "Uniqlo 3D Cut Seamless Down Parka Hard Wearing Review: 5 Pros, 2 Fixes",
            "Video_Timestamp": "2022-09-07T17:01:26Z",
            "Video_View_Count": 21690,
            "Video_Likes": 184
        },
        {
            "Video_kind": "youtube#video",
            "Video_ID": "Dw-Jtf21lkc",
            "Video_Title": "Best Puffer Jackets from $-$$$$",
            "Video_Timestamp": "2022-01-24T17:00:13Z",
            "Video_View_Count": 4340,
            "Video_Likes": 183
        },
        {
            "Video_kind": "youtube#video",
            "Video_ID": "RRotJt2YjYQ",
            "Video_Title": "HOW TO WASH DOWN JACKETS & SLEEPING BAGS",
            "Video_Timestamp": "2022-08-10T11:00:14Z",
            "Video_View_Count": 25062,
            "Video_Likes": 178
        },
        {
            "Video_kind": "youtube#video",
            "Video_ID": "mt9OqsmqcP4",
            "Video_Title": "Top 5 puffer jackets for winter 22/23!",
            "Video_Timestamp": "2022-11-28T03:29:53Z",
            "Video_View_Count": 5990,
            "Video_Likes": 176
        },
        {
            "Video_kind": "youtube#video",
            "Video_ID": "5Iuz2UQ_sbE",
            "Video_Title": "\u301040\u4ee350\u4ee3\u30e6\u30cb\u30af\u30edGU\u30112023\u30ec\u30c7\u30a3\u30fc\u30b9\u2605\u30c0\u30a6\u30f3\u30b8\u30e3\u30b1\u30c3\u30c8\uff06\u30b3\u30fc\u30c8\uff14\u9078\u30b3\u30fc\u30c7\u53b3\u9078\u51ac\u30a2\u30a6\u30bf\u30fcUNIQLO\u30a6\u30eb\u30c8\u30e9\u30e9\u30a4\u30c8\u30c0\u30a6\u30f3\u30ea\u30e9\u30c3\u30af\u30b9\u30b8\u30e3\u30b1\u30c3\u30c8\\\u30b7\u30e3\u30a4\u30cb\u30fc\u30dc\u30ea\u30e5\u30fc\u30e0\u30b8\u30e3\u30b1\u30c3\u30c8\\\u30ed\u30f3\u30b0\u30b3\u30fc\u30c8",
            "Video_Timestamp": "2022-12-29T12:15:57Z",
            "Video_View_Count": 96996,
            "Video_Likes": 173
        },
        {
            "Video_kind": "youtube#video",
            "Video_ID": "CPl73U_DVwo",
            "Video_Title": "\u3010UNIQLO\u3011\u5927\u4eba\u306b\u4f3c\u5408\u3046\u30c0\u30a6\u30f3\u30b3\u30fc\u30c8!!\u5927\u4eba\u6c17\u30b7\u30fc\u30ba\u6700\u65b0\u4f5c\u30cf\u30a4\u30d6\u30ea\u30c3\u30c9\u30c0\u30a6\u30f3\u30b3\u30fc\u30c8\u5fb9\u5e95\u30ec\u30d3\u30e5\u30fc!!\u3010\u6700\u901f\u3011",
            "Video_Timestamp": "2022-11-03T11:05:50Z",
            "Video_View_Count": 32370,
            "Video_Likes": 155
        },
        {
            "Video_kind": "youtube#video",
            "Video_ID": "avbXEhddLO0",
            "Video_Title": "Puffer Jacket Care 101: How to Wash and Maintain Your Puffer Jacket | Best Choices",
            "Video_Timestamp": "2022-12-07T14:00:11Z",
            "Video_View_Count": 19970,
            "Video_Likes": 145
        },
        {
            "Video_kind": "youtube#video",
            "Video_ID": "FJJlV0vTxs4",
            "Video_Title": "\u3010\u30e6\u30cb\u30af\u30ed2022\u79cb\u51ac\u3011\u30a6\u30eb\u30c8\u30e9\u30e9\u30a4\u30c8\u30c0\u30a6\u30f3\u30b8\u30e3\u30b1\u30c3\u30c8\uff083D\u30ab\u30c3\u30c8\uff09\u304c\u3055\u3089\u306b\u9032\u5316\uff01 UNIQLO2022AW",
            "Video_Timestamp": "2022-06-30T08:25:06Z",
            "Video_View_Count": 40418,
            "Video_Likes": 125
        },
        {
            "Video_kind": "youtube#video",
            "Video_ID": "WU3Um45jqrQ",
            "Video_Title": "UNIQLO Review of Ultra Warm Hybrid Down Coat",
            "Video_Timestamp": "2022-12-19T19:34:10Z",
            "Video_View_Count": 12378,
            "Video_Likes": 117
        },
        {
            "Video_kind": "youtube#video",
            "Video_ID": "0MUFW2DB_yc",
            "Video_Title": "\u30109\u67085\u65e5\u767a\u58f2\u3011UNIQLO(\u30e6\u30cb\u30af\u30ed)\u304a\u3059\u3059\u3081\u79cb\u51ac\u65b0\u4f5c\u30a2\u30a4\u30c6\u30e07\u9078",
            "Video_Timestamp": "2022-09-05T10:01:00Z",
            "Video_View_Count": 9196,
            "Video_Likes": 101
        }
    ]
}